{
	"archive" : {},
	"artifacts" : 
	[
		{
			"path" : "Hazel/libimgui.a"
		}
	],
	"backtrace" : 1,
	"backtraceGraph" : 
	{
		"commands" : 
		[
			"add_library",
			"add_compile_options",
			"add_compile_definitions",
			"target_include_directories"
		],
		"files" : 
		[
			"Hazel/CMakeLists.txt",
			"CMakeLists.txt"
		],
		"nodes" : 
		[
			{
				"file" : 0
			},
			{
				"command" : 0,
				"file" : 0,
				"line" : 64,
				"parent" : 0
			},
			{
				"file" : 1
			},
			{
				"command" : 1,
				"file" : 1,
				"line" : 15,
				"parent" : 2
			},
			{
				"command" : 2,
				"file" : 0,
				"line" : 53,
				"parent" : 0
			},
			{
				"command" : 3,
				"file" : 0,
				"line" : 80,
				"parent" : 0
			}
		]
	},
	"compileGroups" : 
	[
		{
			"compileCommandFragments" : 
			[
				{
					"fragment" : "-g  "
				},
				{
					"backtrace" : 3,
					"fragment" : "-fPIC"
				},
				{
					"fragment" : "-std=gnu++17"
				}
			],
			"defines" : 
			[
				{
					"backtrace" : 4,
					"define" : "GLFW_INCLUDE_NONE"
				}
			],
			"includes" : 
			[
				{
					"backtrace" : 5,
					"path" : "/home/demijan/Projects/Engine/Hazel/src"
				}
			],
			"language" : "CXX",
			"sourceIndexes" : 
			[
				0,
				1,
				2,
				3,
				4,
				5,
				6
			]
		}
	],
	"id" : "imgui::@c312927d72e11e7b372f",
	"name" : "imgui",
	"nameOnDisk" : "libimgui.a",
	"paths" : 
	{
		"build" : "Hazel",
		"source" : "Hazel"
	},
	"sourceGroups" : 
	[
		{
			"name" : "Source Files",
			"sourceIndexes" : 
			[
				0,
				1,
				2,
				3,
				4,
				5,
				6
			]
		}
	],
	"sources" : 
	[
		{
			"backtrace" : 1,
			"compileGroupIndex" : 0,
			"path" : "Hazel/vendor/ImGUI/backends/imgui_impl_glfw.cpp",
			"sourceGroupIndex" : 0
		},
		{
			"backtrace" : 1,
			"compileGroupIndex" : 0,
			"path" : "Hazel/vendor/ImGUI/backends/imgui_impl_opengl3.cpp",
			"sourceGroupIndex" : 0
		},
		{
			"backtrace" : 1,
			"compileGroupIndex" : 0,
			"path" : "Hazel/vendor/ImGUI/imgui.cpp",
			"sourceGroupIndex" : 0
		},
		{
			"backtrace" : 1,
			"compileGroupIndex" : 0,
			"path" : "Hazel/vendor/ImGUI/imgui_demo.cpp",
			"sourceGroupIndex" : 0
		},
		{
			"backtrace" : 1,
			"compileGroupIndex" : 0,
			"path" : "Hazel/vendor/ImGUI/imgui_draw.cpp",
			"sourceGroupIndex" : 0
		},
		{
			"backtrace" : 1,
			"compileGroupIndex" : 0,
			"path" : "Hazel/vendor/ImGUI/imgui_widgets.cpp",
			"sourceGroupIndex" : 0
		},
		{
			"backtrace" : 1,
			"compileGroupIndex" : 0,
			"path" : "Hazel/vendor/ImGUI/imgui_tables.cpp",
			"sourceGroupIndex" : 0
		}
	],
	"type" : "STATIC_LIBRARY"
}
